LICENSE
udft/__init__.py
udft/py.typed
udft/test_hnorm.py
udft/udft.py
udft-3.6.1.dist-info/LICENSE
udft-3.6.1.dist-info/METADATA
udft-3.6.1.dist-info/WHEEL
udft-3.6.1.dist-info/RECORD
