Metadata-Version: 2.1
Name: udft
Version: 3.6.1
Summary: Unitary discrete Fourier Transform (and related)
Home-page: https://udft.readthedocs.io/en/stable/
License: Public Domain
Keywords: fft,orthonormal
Author: François Orieux
Author-email: francois.orieux@universite-paris-saclay.fr
Maintainer: François Orieux
Maintainer-email: francois.orieux@universite-paris-saclay.fr
Requires-Python: >=3.8,<4
Classifier: Development Status :: 5 - Production/Stable
Classifier: Intended Audience :: Developers
Classifier: Intended Audience :: Science/Research
Classifier: License :: Other/Proprietary License
Classifier: Operating System :: OS Independent
Classifier: Programming Language :: Python :: 3
Classifier: Programming Language :: Python :: 3.8
Classifier: Programming Language :: Python :: 3.9
Classifier: Programming Language :: Python :: 3.10
Classifier: Programming Language :: Python :: 3.11
Classifier: Programming Language :: Python :: 3.12
Classifier: Programming Language :: Python :: 3.13
Classifier: Programming Language :: Python :: Implementation :: CPython
Classifier: Topic :: Scientific/Engineering
Classifier: Topic :: Scientific/Engineering :: Mathematics
Classifier: Typing :: Typed
Provides-Extra: fftw
Requires-Dist: numpy (>=1.20.2,<2.0.0)
Requires-Dist: pyFFTW (>=0.12.0,<0.13.0) ; extra == "fftw"
Project-URL: Author webpage, https://pro.orieux.fr/
Project-URL: Bug Tracker, https://github.com/forieux/udft/issues
Project-URL: Documentation, https://udft.readthedocs.io/en/stable/
Project-URL: Repository, https://github.com/forieux/udft/
